LICENSE
README.rst
config/config.toml.example
hotness/__init__.py
hotness/builders/__init__.py
hotness/builders/builder.py
hotness/builders/koji.py
hotness/common/__init__.py
hotness/common/rpm.py
hotness/config.py
hotness/databases/__init__.py
hotness/databases/cache.py
hotness/databases/database.py
hotness/databases/redis.py
hotness/domain/__init__.py
hotness/domain/package.py
hotness/exceptions/__init__.py
hotness/exceptions/base_exception.py
hotness/exceptions/builder_exception.py
hotness/exceptions/download_exception.py
hotness/exceptions/http_exception.py
hotness/exceptions/notifier_exception.py
hotness/exceptions/patcher_exception.py
hotness/hotness_consumer.py
hotness/notifiers/__init__.py
hotness/notifiers/bugzilla.py
hotness/notifiers/fedora_messaging.py
hotness/notifiers/notifier.py
hotness/patchers/__init__.py
hotness/patchers/bugzilla.py
hotness/patchers/patcher.py
hotness/requests/__init__.py
hotness/requests/build_request.py
hotness/requests/insert_data_request.py
hotness/requests/notify_request.py
hotness/requests/package_request.py
hotness/requests/request.py
hotness/requests/retrieve_data_request.py
hotness/requests/submit_patch_request.py
hotness/responses/__init__.py
hotness/responses/response.py
hotness/responses/response_failure.py
hotness/responses/response_success.py
hotness/use_cases/__init__.py
hotness/use_cases/insert_data_use_case.py
hotness/use_cases/notify_user_use_case.py
hotness/use_cases/package_check_use_case.py
hotness/use_cases/package_scratch_build_use_case.py
hotness/use_cases/retrieve_data_use_case.py
hotness/use_cases/submit_patch_use_case.py
hotness/validators/__init__.py
hotness/validators/mdapi.py
hotness/validators/pagure.py
hotness/validators/pdc.py
hotness/validators/validator.py
the_new_hotness-1.2.4.dist-info/LICENSE
the_new_hotness-1.2.4.dist-info/METADATA
the_new_hotness-1.2.4.dist-info/WHEEL
the_new_hotness-1.2.4.dist-info/RECORD
