Metadata-Version: 2.1
Name: the-new-hotness
Version: 1.2.4
Summary: A fedora messaging consumer that files bugzilla bugs for upstream releases
Home-page: https://github.com/fedora-infra/the-new-hotness
License: GPL-2.0-or-later
Author: Ralph Bean
Author-email: rbean@redhat.com
Maintainer: Michal Konecny
Maintainer-email: mkonecny@redhat.com
Requires-Python: >=3.8.1,<4.0.0
Classifier: License :: OSI Approved :: GNU General Public License v2 or later (GPLv2+)
Classifier: Programming Language :: Python :: 3
Classifier: Programming Language :: Python :: 3.9
Classifier: Programming Language :: Python :: 3.10
Classifier: Programming Language :: Python :: 3.11
Classifier: Programming Language :: Python :: 3.10
Classifier: Programming Language :: Python :: 3.11
Classifier: Programming Language :: Python :: 3.8
Classifier: Programming Language :: Python :: 3.9
Requires-Dist: anitya-schema (>=2.0.1,<3.0.0)
Requires-Dist: fedora-messaging (>=3.1.0,<4.0.0)
Requires-Dist: fedora-messaging-the-new-hotness-schema (>=1.1.2,<2.0.0)
Requires-Dist: koji (>=1.30.0,<2.0.0)
Requires-Dist: python-bugzilla (>=3.2.0,<4.0.0)
Requires-Dist: redis (>=4.3.4,<5.0.0)
Requires-Dist: requests (>=2.28.1,<3.0.0)
Project-URL: Documentation, https://the-new-hotness.readthedocs.io
Project-URL: Repository, https://github.com/fedora-infra/the-new-hotness
